nntrf/__init__.py
nntrf/loss.py
nntrf/metrics.py
nntrf/utils.py
nntrf/models/__init__.py
nntrf/models/composite.py
nntrf/models/linear.py
nntrf/models/nonlinear.py
nntrf-1.0.4.dist-info/licenses/LICENSE
nntrf-1.0.4.dist-info/METADATA
nntrf-1.0.4.dist-info/WHEEL
nntrf-1.0.4.dist-info/top_level.txt
nntrf-1.0.4.dist-info/RECORD
